ndpyramid/__init__.py
ndpyramid/_version.py
ndpyramid/coarsen.py
ndpyramid/common.py
ndpyramid/create.py
ndpyramid/regrid.py
ndpyramid/reproject.py
ndpyramid/resample.py
ndpyramid/testing.py
ndpyramid/utils.py
ndpyramid-0.4.0.dist-info/LICENSE
ndpyramid-0.4.0.dist-info/METADATA
ndpyramid-0.4.0.dist-info/WHEEL
ndpyramid-0.4.0.dist-info/top_level.txt
ndpyramid-0.4.0.dist-info/RECORD
