Metadata-Version: 2.1
Name: ndpyramid
Version: 0.4.0
Summary: A small utility for generating ND array pyramids using Xarray and Zarr
Author-email: CarbonPlan <tech@carbonplan.org>
License: MIT
Project-URL: repository, https://github.com/carbonplan/ndpyramid
Classifier: Development Status :: 4 - Beta
Classifier: License :: OSI Approved :: MIT License
Classifier: Operating System :: OS Independent
Classifier: Intended Audience :: Science/Research
Classifier: Programming Language :: Python
Classifier: Programming Language :: Python :: 3
Classifier: Programming Language :: Python :: 3.10
Classifier: Programming Language :: Python :: 3.11
Classifier: Programming Language :: Python :: 3.12
Classifier: Topic :: Scientific/Engineering
Requires-Python: >=3.10
License-File: LICENSE
Requires-Dist: cf_xarray>=0.8.0
Requires-Dist: xarray[complete]>=2024.10.0
Requires-Dist: zarr
Requires-Dist: pydantic>=1.10
Requires-Dist: pyproj
Requires-Dist: rasterio
Requires-Dist: numpy
Provides-Extra: complete
Requires-Dist: ndpyramid[dask,jupyter,xesmf]; extra == "complete"
Requires-Dist: mercantile; extra == "complete"
Requires-Dist: cftime; extra == "complete"
Requires-Dist: scipy; extra == "complete"
Requires-Dist: rioxarray; extra == "complete"
Provides-Extra: dask
Requires-Dist: dask[complete]; extra == "dask"
Requires-Dist: pyresample; extra == "dask"
Provides-Extra: jupyter
Requires-Dist: notebook; extra == "jupyter"
Requires-Dist: ipytree>=0.2.2; extra == "jupyter"
Requires-Dist: ipywidgets>=8.0.0; extra == "jupyter"
Requires-Dist: matplotlib; extra == "jupyter"
Provides-Extra: xesmf
Requires-Dist: xesmf>=0.8; extra == "xesmf"
Provides-Extra: test
Requires-Dist: ndpyramid[complete]; extra == "test"
Requires-Dist: pre-commit; extra == "test"
Requires-Dist: pytest-benchmark; extra == "test"
Requires-Dist: pytest-codspeed; extra == "test"
Requires-Dist: pytest-cov; extra == "test"
Requires-Dist: pytest-mypy; extra == "test"
Requires-Dist: pytest; extra == "test"
